meteolux/__init__.py
meteolux/async_api.py
meteolux/exceptions.py
meteolux/models.py
python_meteolux-0.1.2.dist-info/METADATA
python_meteolux-0.1.2.dist-info/WHEEL
python_meteolux-0.1.2.dist-info/RECORD
